pyrflink/__init__.py
pyrflink/dummyserial.py
pyrflink/lowlevel.py
pyrflink/test.py
pyrflink/data/dummyserial_all.conf
pyrflink/data/dummyserial_sensor1.conf
pyrflink/examples/example.py
pyrflink/examples/repeater.py
pyrflink-0.0.3.dist-info/DESCRIPTION.rst
pyrflink-0.0.3.dist-info/METADATA
pyrflink-0.0.3.dist-info/RECORD
pyrflink-0.0.3.dist-info/WHEEL
pyrflink-0.0.3.dist-info/metadata.json
pyrflink-0.0.3.dist-info/top_level.txt
