Metadata-Version: 2.0
Name: pyrflink
Version: 0.0.3
Summary: A Python library for interfacing with RFLink hardware
Home-page: https://pypi.python.org/pypi/pyrflink
Author: mjj4791
Author-email: mjj4791@gmail.com
License: MIT
Keywords: rflink 433mhz domotica tranceiver
Platform: UNKNOWN
Classifier: Development Status :: 3 - Alpha
Classifier: Intended Audience :: Developers
Classifier: License :: OSI Approved :: MIT License
Classifier: Programming Language :: Python :: 3
Classifier: Programming Language :: Python :: 3.3
Classifier: Programming Language :: Python :: 3.4
Classifier: Programming Language :: Python :: 3.5
Requires-Dist: pyserial
